{"description":"","displayName":"BackersOpenCollective","methods":[{"name":"onUpdate","docblock":null,"modifiers":[],"params":[{"name":"prevProps","type":null}],"returns":null},{"name":"getMembers","docblock":null,"modifiers":[],"params":[],"returns":null},{"name":"sort","docblock":null,"modifiers":[],"params":[{"name":"backers","type":null},{"name":"sortDirection","type":null}],"returns":null}],"props":{"className":{"type":{"name":"string"},"required":false,"description":"Class name applied of the container","defaultValue":{"value":"''","computed":false}},"style":{"type":{"name":"objectOf","value":{"name":"any"}},"required":false,"description":"Css style applied to the component","defaultValue":{"value":"{}","computed":false}},"imageRounded":{"type":{"name":"bool"},"required":false,"description":"If true the image will be rounded as a circle","defaultValue":{"value":"true","computed":false}},"imageBordered":{"type":{"name":"bool"},"required":false,"description":"If true the image will have a solid border","defaultValue":{"value":"true","computed":false}},"imageGray":{"type":{"name":"bool"},"required":false,"description":"If true the image doesn't show colors","defaultValue":{"value":"false","computed":false}},"collective":{"type":{"name":"string"},"required":true,"description":"Name of collective in opencollective."},"sortDirection":{"type":{"name":"string"},"required":false,"description":"Sort direction to show the list of backers","defaultValue":{"value":"'desc'","computed":false}},"loadingClass":{"type":{"name":"string"},"required":false,"description":"CSS class for loading animation","defaultValue":{"value":"'fa fa-circle-o-notch fa-spin'","computed":false}},"loadingText":{"type":{"name":"string"},"required":false,"description":"Loading text to show","defaultValue":{"value":"'Loading...'","computed":false}}},"filename":"/components/BackersOpenCollective/BackersOpenCollective.jsx"}